lrtools/__init__.py
lrtools/binary.py
lrtools/jsonformat.py
lrtools/track.py
lrtools/trkformat.py
lrtools/utils.py
lrtools-1.0.3.dist-info/METADATA
lrtools-1.0.3.dist-info/WHEEL
lrtools-1.0.3.dist-info/top_level.txt
lrtools-1.0.3.dist-info/RECORD
