Metadata-Version: 2.1
Name: lrtools
Version: 1.0.3
Summary: Python library for loading and writing Line Rider tracks
Home-page: https://github.com/Conqu3red/trk-python
Author: Conqu3red
License: UNKNOWN
Platform: UNKNOWN
Requires-Python: >=3.6
Requires-Dist: vector-2d (>=1.5.2)
